tdrpa/bot2.exe
tdrpa/eeee.cp38-win_amd64.pyd
tdrpa.tdcore2-0.0.5.dist-info/METADATA
tdrpa.tdcore2-0.0.5.dist-info/WHEEL
tdrpa.tdcore2-0.0.5.dist-info/top_level.txt
tdrpa.tdcore2-0.0.5.dist-info/RECORD
